README.rst
pcd.py
setup.py
persistent_crypto_dict.egg-info/PKG-INFO
persistent_crypto_dict.egg-info/SOURCES.txt
persistent_crypto_dict.egg-info/dependency_links.txt
persistent_crypto_dict.egg-info/requires.txt
persistent_crypto_dict.egg-info/top_level.txt