Metadata-Version: 1.1
Name: persistent-crypto-dict
Version: 0.5.0
Summary: UNKNOWN
Home-page: http://packages.python.org/persistent_crypto_dict
Author: Stefan Marsiske
Author-email: stefan.marsiske@gmail.com
License: BSD
Keywords: crypto collections container persistency cache
Platform: UNKNOWN
Classifier: Development Status :: 4 - Beta
Classifier: License :: OSI Approved :: BSD License
Classifier: Topic :: Security :: Cryptography
